setup.py
django_xmpp_backends/__init__.py
django_xmpp_backends/auth_backends.py
django_xmpp_backends/models.py
django_xmpp_backends.egg-info/PKG-INFO
django_xmpp_backends.egg-info/SOURCES.txt
django_xmpp_backends.egg-info/dependency_links.txt
django_xmpp_backends.egg-info/requires.txt
django_xmpp_backends.egg-info/top_level.txt