Metadata-Version: 1.1
Name: django-xmpp-backends
Version: 0.1
Summary: Convenience utilities for using xmpp-backends in Django.
Home-page: https://github.com/mathiasertl/django-xmpp-backends
Author: Mathias Ertl
Author-email: mati@jabber.at
License: GNU General Public License (GPL) v3
Platform: UNKNOWN
Classifier: Development Status :: 4 - Beta
Classifier: Environment :: Web Environment
Classifier: Framework :: Django
Classifier: Intended Audience :: System Administrators
Classifier: License :: OSI Approved :: GNU General Public License v3 or later (GPLv3+)
Classifier: Operating System :: OS Independent
Classifier: Programming Language :: Python
Classifier: Programming Language :: Python :: 2
Classifier: Programming Language :: Python :: 2.7
Classifier: Programming Language :: Python :: 3
Classifier: Programming Language :: Python :: 3.4
Classifier: Programming Language :: Python :: 3.5
Classifier: Topic :: Internet :: WWW/HTTP
